setup.py
lGridFs/__init__.py
lGridFs/baseModel.py
lgridfs.egg-info/PKG-INFO
lgridfs.egg-info/SOURCES.txt
lgridfs.egg-info/dependency_links.txt
lgridfs.egg-info/top_level.txt