Metadata-Version: 1.0
Name: lgridfs
Version: 0.1.0
Summary: split upload file into mongodb
Home-page: https://github.com/bigpangl
Author: bigpangl
Author-email: bigpangl@163.com
License: UNKNOWN
Platform: UNKNOWN
